sevenbridges/__init__.py
sevenbridges/graphcreator.py
sevenbridges/new_joke.py
src/__init__.py
sevenbridges-0.0.19.dist-info/LICENSE
sevenbridges-0.0.19.dist-info/METADATA
sevenbridges-0.0.19.dist-info/WHEEL
sevenbridges-0.0.19.dist-info/top_level.txt
sevenbridges-0.0.19.dist-info/RECORD
