Metadata-Version: 2.1
Name: sevenbridges
Version: 0.0.19
Summary: UNKNOWN
Home-page: https://pypi.org/project/sevenbridges
Author: 
Author-email: 
License: UNKNOWN
Platform: UNKNOWN
Requires-Python: >=3.8
Requires-Dist: pandas
Requires-Dist: networkx
Requires-Dist: numpy
Requires-Dist: scikit-learn
Requires-Dist: scipy
